[{"code": "C29", "name": "航母机动部队，开始演习！", "id": "330", "desc": "航母机动部队演习任务：编成航空母舰旗舰和僚舰1艘，共2艘以上，并含有驱逐舰2艘的航母机动部队。", "memo": "奖励:以下奖励三选一：九九式艦爆×4,彗星×2,开发资材×3,以下奖励三选一：零式艦戦21型×3,零式艦戦52型×2,洋上補給", "memo2": "空母系旗舰并携带至少另1艘空母系以及至少2只驱逐舰的舰队在一个任务周期内取得演习胜利4次", "pre": ["C9", "Bd1"], "cover": "cover"}
,{"code": "C38", "name": "「十八驱」演习！", "id": "337", "desc": "驱逐舰演习任务：编成包含第十八驱逐队『霞』『霰』『阳炎』『不知火』四只舰娘在内的演习舰队。使用该舰队于本日内演习达成三次以上『S胜』！精锐十八驱永无衰落之日！", "memo": "奖励:间宫×1,以下奖励三选一：大発動艇×1,12cm30連装噴進砲×2,改修资材×3", "memo2": "※季常任务,霞+霰+阳炎+不知火+任意2舰娘，单日内取得3次演习S胜。", "pre": [], "cover": "cover"}
,{"code": "C42", "name": "「十九驱」演习！", "id": "339", "desc": "驱逐舰演习任务：包含第十九驱逐队「矶波」「浦波」「绫波」「敷波」的4只编成演习舰队。使用此舰队达成本日演习【S判定】胜利3次以上！精锐十九驱，那么，好好看着哦！", "memo": "奖励:以下奖励二选一：间宫,改修资材×3,以下奖励三选一：三式爆雷投射機,12.7cm連装砲B型改二,开发资材×8", "memo2": "※季常任务,包含第十九驱逐队(磯波、浦波、綾波、敷波)的舰队在任务周期内取得3次S胜,※任务进度变化,50%(1/3)→80%(2/3)→達成(3/3)", "pre": ["C38", "A72"], "cover": "cover"}
,{"code": "C44", "name": "小舰艇群演习强化任务", "id": "342", "desc": "编成包含4艘驱逐舰或海防舰(可以加入1艘轻巡级)的演习舰队，使用该演习舰队在一日内达成4次以上【A胜】！", "memo": "奖励:以下奖励二选一：开发资材×4,九五式爆雷,以下奖励三选一：零式水上偵察機×2,25mm単装機銃×3,高速修复材×4", "memo2": "※季常任务,驱逐与海防合计4只(其中可以含1只轻巡级)+自由舰种2只，一日内A胜以上4次。", "pre": [], "cover": "cover"}
,{"code": "Bq1", "name": "冲之岛海域迎击战！", "id": "822", "desc": "有力的舰队反复投入2-4 ，迎击侵攻的敌机动部队，将他们消灭！", "memo": "奖励:改修资材*5 间宫*1", "memo2": "以任意舰队进击2-4，赢得BOSS点战斗2次S胜利。", "pre": ["B19", "Bm6"], "cover": "cover"}
,{"code": "Bq2", "name": "战果扩张任务！「Z作战」前段作战", "id": "854", "desc": "于我军第一舰队集中配置精锐舰队，以此精锐舰队，摧毁2-4 、6-1 、6-3 、6-4 的敌军战力！", "memo": "奖励:战果*350,改修资材*4 伊良湖*3", "memo2": "以任意舰队，在2-4、6-1、6-3Boss点取得A胜利以上，在6-4Boss点取得S胜利。", "pre": ["B91", "Bw2"], "cover": "cover"}
,{"code": "Bq3", "name": "强行运输舰队，拔锚！", "id": "861", "desc": "航路护卫任务：以两艘航空战舰(或者补给舰)为核心编成舰队，在1-6 实施运输船队护卫作战。完成该运输作战两次！", "memo": "奖励:高速修复材*4,洋上补给*1", "memo2": "※季常任务,※1-6通关两次(到达目的地),※阵容：(航空战舰+补给舰)*2+任意船舰*4,※任务前置待验证。,伊势改二也可以作为航空战舰完成此任务", "pre": ["B10"], "cover": "cover"}
,{"code": "Bq4", "name": "实施前线航空侦察！", "id": "862", "desc": "侦察任务：以一艘水上机母舰和两艘轻巡洋舰为核心编成侦察舰队，在中部海域6-3 展开，反复实施航空侦察作战「K作战」！进一步捕捉该海域敌军舰队，击破敌军战力！", "memo": "奖励:开发资材*8,改修资材*4", "memo2": "※季常任务,※在6-3Boss点取得两次A胜利,※阵容：水上机母舰*1+轻巡洋舰*2+任意船舰*3,※其他任务前置待验证。", "pre": ["Bq3", "B91"], "cover": "cover"}
,{"code": "Bq5", "name": "实施北方海域警备吧！", "id": "873", "desc": "北方海域警备任务：实施北方海域警备强化。以包含一艘以上轻巡的舰队，于3-1 、3-2 、3-3 展开，实施北方海域方向的警备，并确保制海权！", "memo": "奖励:战斗粮食*1,以下奖励三选一,,12.7cm連装砲C型改二★3*1,,特制家具职人*1,,勋章*1,。", "memo2": "3-1，3-2，3-3boss点各A胜一次,阵容：1cl+5任意舰娘。", "pre": [], "cover": "cover"}
,{"code": "Bq6", "name": "精锐「三一驱」，突入铁底海域！", "id": "875", "desc": "强行东京急行任务：以精锐“三一驱”第一小队作为护卫战力编成突入舰队，投入至5-4|南方沙门海域，突入铁底海峡，并以实力排除展开于该海域的敌方舰艇，反复完成强行鼠输送作战！", "memo": "奖励:以下奖励三选一：13号对空电探*2,22号对水上电探*2,战斗详报*1,以下奖励二选一：新型火炮兵装资材*1,礼物箱*1", "memo2": "季常任务,5-4 BOSS点S胜2次。,长波|长波改二，配以高波|高波改，冲波|冲波改或朝霜|朝霜改中的一艘，加上除此之外的其他舰编成舰队。", "pre": ["A83", "Bq5"], "cover": "cover"}
,{"code": "Bq7", "name": "新编成「三川舰队」，突入铁底海峡！", "id": "888", "desc": "铁底海峡战果扩张：「鸟海」「青叶」「衣笠」「加古」「古鹰」「天龙」「夕张」中的任意4艘包含在内的突入舰队编成。南方海域前段以及萨沃岛海域、所罗门海域突入(5-1、5-3、5-4)，消灭敌舰队！", "memo": "奖励:战果+200,,以下奖励二选一：勋章x1,改修资材x5", "memo2": "※「南方海域前面」(5-1),「サブ島沖海域」(5-3),「サーモン海域」(5-4),BOSS点各1回S胜。", "pre": ["B41", "Bw9"], "cover": "cover"}
,{"code": "Bq8", "name": "彻底确保泊地周边海域的安全！", "id": "893", "desc": "泊地近海警戒战果扩张：编成强有力的泊地警戒部队，反复出击镇守府近海、文莱泊地近海、塔威塔威泊地近海！压制各周边海域出没的地方舰船，并捕捉消灭对泊地周边形成威胁的敌方战力！", "memo": "奖励:战果+300,以下奖励三选一：熟練見張員,熟练搭乘员,洋上补给x4", "memo2": "分别出击1-5、7-1、7-2(P1、P2)各3次，且全部取得S胜,季常任务", "pre": ["B125", "Bw1"], "cover": "cover"}
,{"code": "Bq9", "name": "投入空母战力进行补给线的战斗警戒", "id": "894", "desc": "编成包含空母在内的强有力警戒舰队，前往制油所地带沿岸、南西诸岛防卫战、南西诸岛近海、巴士海峡以及东部奥廖尔海进行战斗警戒，捕捉消灭各海域的敌方舰队，确保各海域补给线的安全！", "memo": "奖励:以下奖励二选一：新型航空兵装资材,开发资材x4,以下奖励三选一：彩雲,熟练搭乘员,礼物箱", "memo2": "包含空母系的舰队分别出击1-3、1-4、2-1、2-2、2-3并获得S胜。", "pre": [], "cover": "cover"}
,{"code": "Bq10", "name": "战果扩张任务！“Z作战”后段作战", "id": "872", "desc": "战果扩张作战：将精锐舰艇集中配备于我第一舰队，以该精锐舰队，捕捉并歼灭南西海域塔威塔威泊地海域(7-2)、南方海域萨部岛海域北方(5-5)、中部海域MS诸岛海域(6-2)、及KW环礁海域(6-5)的敌方舰队！", "memo": "奖励:400战果,以下奖励三选一：改修资材×4,伊良湖×3,洋上补给×4", "memo2": "分别出击7-2(P2)、5-5、6-2、6-5并在BOSS点取得S胜。", "pre": ["Bq2"], "cover": "cover"}
,{"code": "Bq11", "name": "南西诸岛方面“海上警备行动”发令！", "id": "284", "desc": "海上警备任务：派遣包含轻航母或轻巡级1艘、驱逐舰或海防舰共3艘以上的海上护卫舰队，实施南1号作战(1-4)、西南诸岛哨戒(2-1)、柳作战(2-2)、和奥廖尔哨戒(2-3)，歼灭在各作战海域出没的敌舰！", "memo": "奖励:80战果,礼物箱,以下奖励三选一：改修资材×2,九四式爆雷投射機×2,ドラム缶(輸送用)", "memo2": "分别出击1-4、2-1、2-2、2-3并在BOSS点取得S胜。,待验证前置还包括Bw10", "pre": ["Bm8", "C2"], "cover": "cover"}
,{"code": "Bq12", "name": "发令！「西方海域作战」", "id": "845", "desc": "大规模出击任务：西方海域作战发动！编成有力舰队，出击西方海域全海域，完全击破该海域的敌方战力，消灭她们！舰队，向西出发！", "memo": "奖励:330战果,以下奖励三选一：勋章×1,大発動艇×2,新型喷进装备开发资材×1", "memo2": "分别出击4-1、4-2、4-3、4-4、4-5，并在BOSS点取得各一次S胜。", "pre": ["Bq11", "B23"], "cover": "cover"}
,{"code": "Bq13", "name": "扩张「六水战」，向最前线！", "id": "903", "desc": "轻巡「夕张改二」型为旗舰，包含随伴第六水雷战队驱逐舰2艘以上或「由良改二」的舰队，在南方5-1、5-4、中部6-4、6-5海域展开，击灭敌战力！", "memo": "奖励:战果+390,以下奖励三选一：高速修复材×10,勋章×1,新型火炮兵装资材x1", "memo2": "季常任务,【夕张改二(特/丁)】为旗舰，僚舰含有2只以上第六水雷战队成员或【由良改二】(即夕张改二+2六水战驱逐 or 夕张改二+由良改二),5-1，5-4，6-4，6-5的boss点各取得一次S胜利,六水战已实装驱逐：睦月/如月/弥生/卯月/菊月/望月", "pre": ["B141"], "cover": "cover"}
,{"code": "D24", "name": "强化海上通商航路警戒！", "id": "426", "desc": "远征任务：完成远征任务「警备任务」(远征3)「对潜警戒任务」(远征4)「海上护卫任务」(远征5)「强行侦察任务」(远征10)，压制敌军通商破坏舰队，确保海上通商航路的安全！", "memo": "奖励:开发资材*4,战斗粮食*2", "memo2": "※季常任务,※前述远征各完成一次,※任务前置待验证。", "pre": ["B63", "F16"], "cover": "cover"}
,{"code": "D26", "name": "压制侵入近海的敌方潜艇！", "id": "428", "desc": "敌方潜艇压制任务：多次实施远征任务“对潜警戒任务”“海峡警备任务”“长时间对潜警戒”，压制侵入近海的敌方潜艇，从我方领海中驱逐出去！", "memo": "奖励:改修资材*3 ,九五式爆雷*1", "memo2": "季常,完成远征4，远征A2，远征A3各2次", "pre": ["D24", "D25"], "cover": "cover"}
,{"code": "F35", "name": "「熟练搭乘员」养成", "id": "637", "desc": "消费勋章x2：以「凤翔」为秘书舰搭载一架练度max及改修max的「九六式舰战」，养成熟练搭乘员！(任务完成后，部队将会被消去)", "memo": "奖励:熟练搭乘员*1,改修资材*4", "memo2": "凤翔装备一个改修Max与练度Max的九六舰战并消耗两个勋章,获得一个熟练搭乘员。,前置任务待验证", "pre": ["B9"], "cover": "cover"}
,{"code": "F39", "name": "主力“陆攻”的采购", "id": "643", "desc": "新采购主力陆上攻击机“一式陆攻”。于工厂废弃零式舰战21型 两个，另准备九六式陆攻一个、九七式舰攻两个！(任务达成后装备消失)", "memo": "奖励:一式陆攻,开发资材*2", "memo2": "需要在季常刷新后做完D9(东京急行一次),注意装备需要解锁，否则不能完成任务", "pre": ["F38", "D9"], "cover": "cover"}
,{"code": "F55", "name": "继续研究新型舾装", "id": "663", "desc": "工厂任务：继续进行新型舾装的开发。废弃10个「大口径主炮」系装备，准备18000钢材！(任务完成后，准备好的资源会消耗掉。能够选择性获得「勋章」或「新型火炮兵装资材」。)", "memo": "奖励:勋章*1,新型火炮兵装资材*1, 以上二者选择其一,开发资材*3", "memo2": "※季常任务", "pre": ["D23"], "cover": "cover"}
,{"code": "F67", "name": "运用装备的综合整备", "id": "675", "desc": "运用装备综合任务：实施装备的综合整备。废弃6架「舰载战斗机」、4个「机枪」装备，并准备好800铝土(本任务会根据时局发生变化)。※任务完成后，准备好的资源会被消耗。", "memo": "奖励:开发资材*4,以下奖励三选一,,一式戦 隼II型*1,,紫電一一型*1,,改修资材*4,。", "memo2": "季常任务", "pre": ["F66"], "cover": "cover"}
,{"code": "F70", "name": "主力舰上战斗机的更新", "id": "678", "desc": "废弃舰上战斗机“九六式舰战”×3，“零式舰战21型”×5。在秘书舰的一号和二号格子中装备“零式舰战52型”。准备铝土4,000！※任务达成后，会消费掉准备的资源。", "memo": "奖励:紫電改二*2,以下奖励二选一：开发资材*8,新型航空兵装资材*1", "memo2": "季常任务", "pre": ["Bd2"], "cover": "cover"}
,{"code": "F72", "name": "对空兵装的整备扩充", "id": "680", "desc": "继续实施对空兵装的整备扩充！废弃“机枪”系装备×4和“电探”系装备×4，准备铝土1,500！※任务达成后会消费掉准备的资源。", "memo": "奖励:以下奖励二选一：10cm连装高角炮*2,12cm30连装喷进炮*2,以下奖励二选一：8cm高角炮*2,开发资材*6", "memo2": "季常任务", "pre": ["F71", "F5"], "cover": "cover"}
,{"code": "F77", "name": "战时改修A型高角炮的量产", "id": "686", "desc": "在特型驱逐舰旗舰的第一格装备「12.7cm連装砲A型改二」改修max，废弃「10cm連装高角砲」x4、「94式高射装置」x1，准备开发资材x30、钢材900、新型火炮兵装x1。", "memo": "奖励:12.7cm連装砲A型改三(戦時改修)+高射装置", "memo2": "季常", "pre": ["F72", "F76"], "cover": "cover"}
,{"code": "F79", "name": "强化航空战力", "id": "688", "desc": "航空战力强化任务：废弃「舰战」「舰爆」「舰攻」「水侦」装备各3个，再准备熟练搭载员×1以及1800铝土！(任务完成后，熟练搭载员×1和1800铝土会被消耗)", "memo": "奖励:以下奖励三选一：零式艦戦32型(熟練),一式戦 隼II型,瑞雲(六三一空)", "memo2": "准备1个熟练搭乘员和1800铝材，废弃舰战、舰爆、舰攻、水侦各3个。,季常任务", "pre": ["F66"], "cover": "cover"}
,{"code": "F90", "name": "工厂运转！为下期作战做准备！", "id": "653", "desc": "废弃6个「14cm单装炮」，并准备好6000家具币以及「35.6cm连装炮」、「九六式舰战」各3个！ ※任务达成后，将消耗掉家具币及必要装备(优先消耗低改修度)。", "memo": "奖励:以下奖励三选一：大発動艇×1,零式艦戦21型×2,九六式陸攻×1,以下奖励三选一：九四式爆雷投射機×3,12cm30連装噴進砲×2,二式12cm迫撃砲改×1", "memo2": "※季常任务,准备6000家具币、35.6cm连装炮×3、九六式舰战×3，然后废弃14cm单装炮×6，任务完成后资源消耗。", "pre": [], "cover": "cover"}
]